LICENSE
MANIFEST.in
README.md
setup.py
django_postgres_loader/__init__.py
django_postgres_loader/load.py
django_postgres_loader/managers.py
django_postgres_loader.egg-info/PKG-INFO
django_postgres_loader.egg-info/SOURCES.txt
django_postgres_loader.egg-info/dependency_links.txt
django_postgres_loader.egg-info/requires.txt
django_postgres_loader.egg-info/top_level.txt
django_postgres_loader/core/__init__.py
django_postgres_loader/core/definitions.py
django_postgres_loader/core/field_updaters.py
django_postgres_loader/core/templates/sql/copy.sql
django_postgres_loader/core/templates/sql/create.sql
django_postgres_loader/core/templates/sql/drop.sql
django_postgres_loader/core/templates/sql/insert__append.sql
django_postgres_loader/core/templates/sql/insert__safe_append.sql
django_postgres_loader/core/templates/sql/insert__update.sql
django_postgres_loader/core/templates/sql/insert__upsert.sql
django_postgres_loader/utils/__init__.py
tests/__init__.py